sharded/__init__.py
sharded/drivers.py
sharded/entity.py
sharded/gateway.py
sharded/repository.py
sharded/schema.py
sharded-0.0.1.dist-info/METADATA
sharded-0.0.1.dist-info/WHEEL
sharded-0.0.1.dist-info/licenses/LICENSE
sharded-0.0.1.dist-info/RECORD
