Metadata-Version: 2.1
Name: sharded
Version: 0.0.1
Summary: data management framework
Project-URL: Homepage, https://github.com/basis-company/sharded.py
Project-URL: Bug Tracker, https://github.com/basis-company/sharded.py/issues
Author-email: Dmitry Krokhin <nekufa@gmail.com>
License-File: LICENSE
Classifier: License :: OSI Approved :: MIT License
Classifier: Operating System :: OS Independent
Classifier: Programming Language :: Python :: 3
Requires-Python: >=3.11
